README.rst
setup.py
nosetest_tracker/__init__.py
nosetest_tracker/app.py
nosetest_tracker.egg-info/PKG-INFO
nosetest_tracker.egg-info/SOURCES.txt
nosetest_tracker.egg-info/dependency_links.txt
nosetest_tracker.egg-info/top_level.txt