Metadata-Version: 1.1
Name: nosetest-tracker
Version: 0.0.3
Summary: Tracking test cases in nose and logs them in xls file
Home-page: https://github.com/Hallborg/nosetest-tracker
Author: Hallborg
Author-email: jesper.hallborg@hotmail.com
License: MIT
Keywords: test development
Platform: UNKNOWN
Classifier: Development Status :: 3 - Alpha
Classifier: Intended Audience :: Developers
Classifier: Topic :: Software Development :: Build Tools
Classifier: License :: OSI Approved :: MIT License
Classifier: Programming Language :: Python :: 2
Classifier: Programming Language :: Python :: 2.6
Classifier: Programming Language :: Python :: 2.7
